safe_migrations/__init__.py
safe_migrations/management/__init__.py
safe_migrations/management/commands/__init__.py
safe_migrations/management/commands/safe_migrations.py
tests/__init__.py
safe_migrations-0.2.0.dist-info/LICENSE
safe_migrations-0.2.0.dist-info/METADATA
safe_migrations-0.2.0.dist-info/WHEEL
safe_migrations-0.2.0.dist-info/top_level.txt
safe_migrations-0.2.0.dist-info/RECORD
