Metadata-Version: 2.1
Name: safe_migrations
Version: 0.2.0
Summary: A Django package to safely generate and apply migrations from historical commits.
Home-page: https://github.com/yourusername/safe_migrations
Author: Mohammad Mohsen Ahmadi
Author-email: mohsenaahmadi@gmail.com
Classifier: Programming Language :: Python :: 3
Classifier: Framework :: Django
Classifier: License :: OSI Approved :: MIT License
Classifier: Operating System :: OS Independent
Requires-Python: >=3.7
License-File: LICENSE
Requires-Dist: Django>=3.2
Requires-Dist: gitpython>=3.1.30
